yamlpal/__init__.py
yamlpal/cli.py
yamlpal/exceptions.py
yamlpal/yaml_parser.py
yamlpal/tests/__init__.py
yamlpal/tests/base.py
yamlpal/tests/test_cli.py
yamlpal/tests/test_find.py
yamlpal/tests/test_find_negative.py
yamlpal/tests/test_insert.py
yamlpal/tests/test_insert_negative.py
yamlpal-0.1.0.dist-info/DESCRIPTION.rst
yamlpal-0.1.0.dist-info/METADATA
yamlpal-0.1.0.dist-info/RECORD
yamlpal-0.1.0.dist-info/WHEEL
yamlpal-0.1.0.dist-info/entry_points.txt
yamlpal-0.1.0.dist-info/metadata.json
yamlpal-0.1.0.dist-info/top_level.txt
